iptables-dynamic/__init__.py
iptables_dynamic/__init__.py
iptables_dynamic-0.2.1.dist-info/DESCRIPTION.rst
iptables_dynamic-0.2.1.dist-info/LICENSE.txt
iptables_dynamic-0.2.1.dist-info/METADATA
iptables_dynamic-0.2.1.dist-info/RECORD
iptables_dynamic-0.2.1.dist-info/WHEEL
iptables_dynamic-0.2.1.dist-info/entry_points.txt
iptables_dynamic-0.2.1.dist-info/metadata.json
iptables_dynamic-0.2.1.dist-info/top_level.txt
