Metadata-Version: 2.0
Name: iptables-dynamic
Version: 0.2.1
Summary: Dynamically save and restore iptables rules for some chain(s)
Home-page: https://github.com/aalireza/iptables-dynamic
Author: Alireza Rafiei (aalireza)
Author-email: mail@rafiei.net
License: BSD 3-clause
Download-URL: https://github.com/aalireza/iptables-dynamic/tarball/0.2.1
Keywords: iptables,save chain,restore chain
Platform: UNKNOWN
Classifier: Development Status :: 4 - Beta
Classifier: Environment :: Console
Classifier: Intended Audience :: Developers
Classifier: Intended Audience :: System Administrators
Classifier: Topic :: System :: Networking :: Firewalls
Classifier: Topic :: Utilities
Classifier: License :: OSI Approved :: BSD License
Classifier: Operating System :: POSIX :: Linux
Classifier: Programming Language :: Python :: 2.6
Classifier: Programming Language :: Python :: 2.7
Classifier: Programming Language :: Python :: 3
Classifier: Programming Language :: Python :: 3.3
Classifier: Programming Language :: Python :: 3.4
Classifier: Programming Language :: Python :: 3.5
